ProbDistro/__init__.py
ProbDistro/base_continuous_distribution.py
ProbDistro/base_discrete_distribution.py
ProbDistro/base_distribution.py
ProbDistro/conversion.py
ProbDistro/continuous_distributions/__init__.py
ProbDistro/continuous_distributions/exponential.py
ProbDistro/continuous_distributions/normal.py
ProbDistro/continuous_distributions/uniform.py
ProbDistro/discrete_distributions/__init__.py
ProbDistro/discrete_distributions/bernoulli.py
ProbDistro/discrete_distributions/binomial.py
ProbDistro/discrete_distributions/discrete_random_variable.py
ProbDistro/discrete_distributions/geometric.py
ProbDistro/discrete_distributions/hypergeometric.py
ProbDistro/discrete_distributions/poisson.py
ProbDistro-1.0.1.dist-info/LICENSE
ProbDistro-1.0.1.dist-info/METADATA
ProbDistro-1.0.1.dist-info/WHEEL
ProbDistro-1.0.1.dist-info/top_level.txt
ProbDistro-1.0.1.dist-info/RECORD
