Metadata-Version: 2.1
Name: ProbDistro
Version: 1.0.1
Summary: A Python package for handeling various continous and discrete randcom variables, including normal/gauss, binomial, poisson, and more
Home-page: https://github.com/CPSuperstore/ProbDistro
Author: Christopher
Author-email: cpsuperstoreinc@gmail.com
License: MIT
Project-URL: Bug Tracker, https://github.com/CPSuperstore/ProbDistro/issues
Project-URL: Documentation, https://github.com/CPSuperstore/ProbDistro
Keywords: PROBABILITY,DISTRIBUTION,NORMAL,UNIFORM,GAUSS,POISSON,BINOMIAL,BERNOULLI,GEOMETRIC,HYPERGEOMETRIC
Platform: UNKNOWN
Classifier: Development Status :: 4 - Beta
Classifier: Intended Audience :: Science/Research
Classifier: Intended Audience :: Developers
Classifier: Intended Audience :: Education
Classifier: License :: OSI Approved :: MIT License
Classifier: Programming Language :: Python :: 3
Classifier: Natural Language :: English
Classifier: Topic :: Education
Classifier: Topic :: Scientific/Engineering :: Information Analysis
Classifier: Topic :: Scientific/Engineering :: Mathematics
Classifier: Topic :: Scientific/Engineering :: Physics
Classifier: Topic :: Software Development :: Libraries
Classifier: Topic :: Utilities
License-File: LICENSE
